MyLabLibraryTAM1/Compiler.py
MyLabLibraryTAM1/Parser.py
MyLabLibraryTAM1/Reader.py
MyLabLibraryTAM1/Struck.py
MyLabLibraryTAM1/Value.py
MyLabLibraryTAM1/__init__.py
MyLabLibraryTAM1/main.py
MyLabLibraryTAM1-0.1.4.dist-info/METADATA
MyLabLibraryTAM1-0.1.4.dist-info/WHEEL
MyLabLibraryTAM1-0.1.4.dist-info/top_level.txt
MyLabLibraryTAM1-0.1.4.dist-info/RECORD
