Metadata-Version: 2.1
Name: MyLabLibraryTAM1
Version: 0.1.4
Summary: Кастомная библиотека по второй лабораторной работе лог. програмирования
Home-page: https://github.com/MitrofanovTimurAlexsandrovich/my_library 
Author: Timur Mitrofanov
Author-email: mitrofanov-t@bk.ru
License: example
Classifier: Programming Language :: Python :: 3
Classifier: Operating System :: OS Independent
Requires-Python: >=3.12
